sphinxcontrib_argdoc-0.1.3-py2.7-nspkg.pth
sphinxcontrib_argdoc-0.1.3.dist-info/top_level.txt
sphinxcontrib_argdoc-0.1.3.dist-info/WHEEL
sphinxcontrib_argdoc-0.1.3.dist-info/RECORD
sphinxcontrib_argdoc-0.1.3.dist-info/namespace_packages.txt
sphinxcontrib_argdoc-0.1.3.dist-info/DESCRIPTION.rst
sphinxcontrib_argdoc-0.1.3.dist-info/METADATA
sphinxcontrib_argdoc-0.1.3.dist-info/zip-safe
sphinxcontrib_argdoc-0.1.3.dist-info/metadata.json
sphinxcontrib/argdoc/ext.py
sphinxcontrib/argdoc/__init__.py
sphinxcontrib/argdoc/test/__init__.py
sphinxcontrib/argdoc/test/test_argdoc.py
sphinxcontrib/argdoc/test/testbuild/sphinxcontrib.argdoc.test.cases.c7_noargdoc_postargdoc.rst
sphinxcontrib/argdoc/test/testbuild/sphinxcontrib.argdoc.test.cases.c9_subsubparsers_postargdoc.rst
sphinxcontrib/argdoc/test/testbuild/sphinxcontrib.argdoc.test.cases.c1_argument_group_postargdoc.rst
sphinxcontrib/argdoc/test/testbuild/sphinxcontrib.argdoc.test.cases.c4_with_long_subparsers_postargdoc.rst
sphinxcontrib/argdoc/test/testbuild/__init__.py
sphinxcontrib/argdoc/test/testbuild/sphinxcontrib.argdoc.test.cases.c6_multiprefix_postargdoc.rst
sphinxcontrib/argdoc/test/testbuild/sphinxcontrib.argdoc.test.cases.c5_with_epilog_postargdoc.rst
sphinxcontrib/argdoc/test/testbuild/sphinxcontrib.argdoc.test.cases.c8_exhaustive_postargdoc.rst
sphinxcontrib/argdoc/test/testbuild/sphinxcontrib.argdoc.test.cases.c3_main_plus_subparsers_postargdoc.rst
sphinxcontrib/argdoc/test/testbuild/sphinxcontrib.argdoc.test.cases.c2_only_subparsers_postargdoc.rst
sphinxcontrib/argdoc/test/testdocroot/sphinxcontrib.argdoc.test.cases.c1_argument_group.rst
sphinxcontrib/argdoc/test/testdocroot/master_toctree.rst
sphinxcontrib/argdoc/test/testdocroot/sphinxcontrib.argdoc.test.cases.c4_with_long_subparsers.rst
sphinxcontrib/argdoc/test/testdocroot/conf.py
sphinxcontrib/argdoc/test/testdocroot/sphinxcontrib.argdoc.test.cases.c2_only_subparsers.rst
sphinxcontrib/argdoc/test/testdocroot/sphinxcontrib.argdoc.test.cases.c3_main_plus_subparsers.rst
sphinxcontrib/argdoc/test/testdocroot/sphinxcontrib.argdoc.test.cases.c7_noargdoc.rst
sphinxcontrib/argdoc/test/testdocroot/sphinxcontrib.argdoc.test.cases.c9_subsubparsers.rst
sphinxcontrib/argdoc/test/testdocroot/sphinxcontrib.argdoc.test.cases.c5_with_epilog.rst
sphinxcontrib/argdoc/test/testdocroot/__init__.py
