Metadata-Version: 2.0
Name: sphinxcontrib-argdoc
Version: 0.1.3
Summary: Sphinx "argdoc" extension
Home-page: http://bitbucket.org/birkenfeld/sphinx-contrib
Author: Joshua Griffin Dunn
Author-email: Joshua Griffin Dunn
License: BSD 3-Clause
Download-URL: http://pypi.python.org/pypi/sphinxcontrib-argdoc
Keywords: sphinx documentation argparse command-line autodoc
Platform: any
Classifier: Development Status :: 5 - Production/Stable
Classifier: Environment :: Plugins
Classifier: Environment :: Web Environment
Classifier: Programming Language :: Python
Classifier: Programming Language :: Python :: 2.7
Classifier: Programming Language :: Python :: 3
Classifier: Framework :: Sphinx :: Extension
Classifier: Topic :: Documentation
Classifier: Topic :: Documentation :: Sphinx
Classifier: Topic :: Software Development :: Documentation
Classifier: Topic :: Text Processing
Classifier: Topic :: Utilities
Classifier: Intended Audience :: Developers
Classifier: License :: OSI Approved :: BSD License
Classifier: Natural Language :: English
Classifier: Operating System :: OS Independent
Requires-Dist: sphinx (>=1.3.1)
Requires-Dist: autodoc (>=0.3)
